recursion2loop/__init__.py
recursion2loop/tree/__init__.py
recursion2loop/tree/tree_node.py
recursion2loop/tree/tree_operations.py
recursion2loop/tree/tree_traversal.py
recursion2loop-0.2.3.dist-info/LICENSE
recursion2loop-0.2.3.dist-info/METADATA
recursion2loop-0.2.3.dist-info/WHEEL
recursion2loop-0.2.3.dist-info/top_level.txt
recursion2loop-0.2.3.dist-info/RECORD
