Metadata-Version: 2.2
Name: recursion2loop
Version: 0.2.3
Summary: conversion of recursive functions to iterative implementations. Optimize your Python code by transforming stack-heavy recursion into efficient loops.
Home-page: https://github.com/AdilKoken/recursion2loop
Author: Adil Köken
Author-email: mail@adilkoken.com
Classifier: Programming Language :: Python :: 3
Classifier: License :: OSI Approved :: MIT License
Classifier: Operating System :: OS Independent
Requires-Python: >=3.9
License-File: LICENSE
Dynamic: author
Dynamic: author-email
Dynamic: classifier
Dynamic: description
Dynamic: description-content-type
Dynamic: home-page
Dynamic: requires-python
Dynamic: summary
